{
    "comment": "是否启用此策略",
    "enable": true,
    "instance": [
        {
            "comment_0": "是否启用此实例",
            "enable": true,
            "comment_1": "ID用于区分不同策略实例的委托",
            "ID": 110,
            "BeginDate": 20170101,
            "comment_2": "可通过增加Data实现多合约多周期引用",
            "Datas": [
                {
                    "Instrument": "rb1805",
                    "IntervalType": "Minute",
                    "Interval": 1
                },
                {
                    "Instrument": "rb1805",
                    "IntervalType": "Day",
                    "Interval": 1
                }
            ],
            "Params": {
                "Lots": 1,
                "MA1": 10,
                "MA2": 20
            }
        }
        
    ]
}